{"url": "http://centuryglobal.ca/site-map/", "title": "Site Map - Century Global Commodities Corporation@@Email@@Facebook@@Instagram@@LinkedIn@@Twitter@@YouTube", "meta_description": NaN, "structured_data": {}, "body_text": "Century Global Commodities Corporation \t\t\t \r\n \n\t\t \n \n You are here:  Home   /  Site Map Site Map \n \n \n \n Contact \n \n\t Careers \n \n \n Corporate \n \n\t About the Company \n\t Advisory Board & Management \n\t Corporate Governance \n\t Directors \n\t Strategic Direction \n\t Strategic Partners \n \n \n Investors \n \n\t 2021 News Releases \n\t 2022 News Releases \n\t 2023 News Releases \n\t 2024 News Releases \n\t Awards and Events \n\t \n\t\t Century receives 2014 CCBC Award for Chinese Investment in Canada \n\t\t Century’s 2013 Iron Ore Conference \n\t\t \n\t\t\t Analyst Coverage and Reports \n\t\t\t Speakers and Presentations \n\t\t \n \n\t\t Labec Century awarded the 2014 Explorer Of The Year Award, CIM Newfoundland Branch \n\t \n \n\t Corporate, Market and Project Presentations \n\t Financial and Management Reports \n\t Investor Relations Contact \n\t Media and Videos \n\t \n\t\t Media Coverage Archive \n\t \n \n\t News Release Archive \n\t News Releases \n \n \n Legal Page \n Projects \n \n\t Black Bird DSO Deposit \n\t Duncan Lake Project \n\t Full Moon Project \n\t Hayot Lake Deposit \n\t Joyce Lake DSO Project \n\t Mineral Resources and Reserves \n\t Technical Reports \n\t Joyce Fact Sheet \n \n \n Site Map \n Social Responsibility \n \n\t Community and Stakeholder Relations \n\t Environmental Responsibility \n\t Health and Safety \n \n \n\n \n CONTACT US \n\t\t\t \r\nEmail:  \r\ncontact@centuryglobal.ca \r\n \n\t\t \n \n STAY CONNECTED \n \n Subscribe \n \r\n \r\n \r\n \r\n \r\n \r\n \r\n \n 7ads6x98y", "markdown_content": ""}